ikkuna/export/__init__.py
ikkuna/export/export.py
ikkuna/export/messages.py
ikkuna/export/subscriber/__init__.py
ikkuna/export/subscriber/condition.py
ikkuna/export/subscriber/hessian_eig.py
ikkuna/export/subscriber/histogram.py
ikkuna/export/subscriber/loss.py
ikkuna/export/subscriber/mean.py
ikkuna/export/subscriber/message_mean.py
ikkuna/export/subscriber/norm.py
ikkuna/export/subscriber/ratio.py
ikkuna/export/subscriber/spectral_norm.py
ikkuna/export/subscriber/subscriber.py
ikkuna/export/subscriber/sum.py
ikkuna/export/subscriber/svcca.py
ikkuna/export/subscriber/test_accuracy.py
ikkuna/export/subscriber/train_accuracy.py
ikkuna/export/subscriber/variance.py
ikkuna/models/__init__.py
ikkuna/models/alexnetmini.py
ikkuna/models/densenet.py
ikkuna/models/fc.py
ikkuna/models/resnet.py
ikkuna/models/vgg.py
ikkuna/utils/__init__.py
ikkuna/utils/module_tree.py
ikkuna/utils/named_module.py
ikkuna/utils/numba.py
ikkuna/utils/utils.py
ikkuna/visualization/__init__.py
ikkuna/visualization/backend.py
ikkuna-0.1.0.post2.dist-info/LICENSE
ikkuna-0.1.0.post2.dist-info/METADATA
ikkuna-0.1.0.post2.dist-info/WHEEL
ikkuna-0.1.0.post2.dist-info/entry_points.txt
ikkuna-0.1.0.post2.dist-info/top_level.txt
ikkuna-0.1.0.post2.dist-info/RECORD
