Metadata-Version: 2.1
Name: ikkuna
Version: 0.1.0.post2
Summary: Ikkuna Neural Network Monitor
Home-page: https://peltarion.github.io/ai_ikkuna/
Author: Rasmus Diederichsen
Author-email: rasmus@peltarion.com
License: UNKNOWN
Keywords: deep-learning,pytorch,neural-networks,machine-learning
Platform: UNKNOWN
Classifier: Development Status :: 3 - Alpha
Classifier: Intended Audience :: Science/Research
Classifier: Topic :: Scientific/Engineering :: Visualization
Classifier: Topic :: Scientific/Engineering :: Artificial Intelligence
Classifier: Programming Language :: Python :: 3.6
Classifier: License :: OSI Approved :: MIT License
Classifier: Intended Audience :: Developers
Requires-Dist: numpy (>=1.15.0)
Requires-Dist: Cython (>=0.28.5)
Requires-Dist: tensorboardX
Requires-Dist: tqdm (>=4.24.0)
Requires-Dist: sphinx-argparse (>=0.2.2)
Requires-Dist: sphinx-rtd-theme (>=0.4.3)
Requires-Dist: matplotlib (>=2.2.0)
Requires-Dist: sphinx (>=1.7.5)
